{
  "modelVersion" : "2.0",
  "id" : "formValidarDifusionEvento",
  "name" : "formValidarDifusionEvento",
  "lastUpdate" : 1618871480214,
  "rows" : [
    [
      {
        "type" : "fragment",
        "dimension" : {
          "xs" : 12,
          "sm" : 12,
          "md" : 12,
          "lg" : 12
        },
        "propertyValues" : {
          "cssClasses" : {
            "type" : "constant",
            "value" : ""
          },
          "hidden" : {
            "type" : "constant",
            "value" : false
          }
        },
        "reference" : "3935e0b8-07fa-4035-99de-bd3b3e209633",
        "hasValidationError" : false,
        "id" : "header",
        "binding" : { }
      }
    ],
    [
      {
        "type" : "fragment",
        "dimension" : {
          "xs" : 12,
          "sm" : 12,
          "md" : 12,
          "lg" : 12
        },
        "propertyValues" : {
          "cssClasses" : {
            "type" : "constant",
            "value" : ""
          },
          "hidden" : {
            "type" : "constant",
            "value" : false
          }
        },
        "reference" : "cd77c8db-e79a-4b71-b86b-32bf8a7d3bbd",
        "hasValidationError" : false,
        "id" : "usuarioSolicitante",
        "binding" : {
          "usuarioSolicitante" : "usuarioSolicitante"
        }
      }
    ],
    [
      {
        "type" : "container",
        "dimension" : {
          "xs" : 12
        },
        "propertyValues" : {
          "cssClasses" : {
            "type" : "constant",
            "value" : ""
          },
          "hidden" : {
            "type" : "constant",
            "value" : false
          },
          "repeatedCollection" : {
            "type" : "variable",
            "value" : ""
          }
        },
        "reference" : "b344a5e0-bd79-4021-9d13-0479ac31a649",
        "hasValidationError" : false,
        "id" : "pbContainer",
        "rows" : [
          [
            {
              "type" : "component",
              "dimension" : {
                "md" : 12,
                "sm" : 12,
                "xs" : 12,
                "lg" : 12
              },
              "propertyValues" : {
                "hidden" : {
                  "type" : "constant",
                  "value" : false
                },
                "level" : {
                  "type" : "constant",
                  "value" : "Level 3"
                },
                "cssClasses" : {
                  "type" : "constant",
                  "value" : ""
                },
                "text" : {
                  "type" : "interpolation",
                  "value" : "{{ task.displayName }}"
                },
                "alignment" : {
                  "type" : "constant",
                  "value" : "center"
                },
                "dimension" : {
                  "type" : "constant",
                  "value" : 12
                }
              },
              "reference" : "c6287b2e-53be-44d9-8826-cd1c57cdee4f",
              "hasValidationError" : false,
              "id" : "pbTitle",
              "description" : ""
            }
          ]
        ]
      }
    ],
    [
      {
        "type" : "formContainer",
        "dimension" : {
          "xs" : 12
        },
        "propertyValues" : {
          "cssClasses" : {
            "type" : "constant",
            "value" : ""
          },
          "hidden" : {
            "type" : "constant",
            "value" : false
          }
        },
        "reference" : "3c9d483f-6594-46fb-a36c-e4b2ed428a0e",
        "hasValidationError" : false,
        "id" : "pbFormContainer",
        "container" : {
          "type" : "container",
          "dimension" : {
            "xs" : 12
          },
          "propertyValues" : { },
          "reference" : "2f0f870f-f495-404c-a31e-eb7a7f95ce0f",
          "hasValidationError" : false,
          "id" : "pbContainer",
          "rows" : [
            [
              {
                "type" : "container",
                "dimension" : {
                  "md" : 12,
                  "sm" : 12,
                  "xs" : 12,
                  "lg" : 12
                },
                "propertyValues" : {
                  "repeatedCollection" : {
                    "type" : "variable",
                    "value" : ""
                  },
                  "hidden" : {
                    "type" : "constant",
                    "value" : false
                  },
                  "cssClasses" : {
                    "type" : "constant",
                    "value" : ""
                  },
                  "dimension" : {
                    "type" : "constant",
                    "value" : 12
                  }
                },
                "reference" : "d4e0d5d9-ad15-4da0-b730-763a0769e8b5",
                "hasValidationError" : false,
                "id" : "pbContainer",
                "rows" : [
                  [
                    {
                      "type" : "container",
                      "dimension" : {
                        "xs" : 6,
                        "sm" : 6,
                        "md" : 6,
                        "lg" : 6
                      },
                      "propertyValues" : {
                        "cssClasses" : {
                          "type" : "constant",
                          "value" : ""
                        },
                        "hidden" : {
                          "type" : "constant",
                          "value" : false
                        },
                        "repeatedCollection" : {
                          "type" : "variable",
                          "value" : ""
                        }
                      },
                      "reference" : "549e474e-e052-48fb-849e-d3a4f3d3dc46",
                      "hasValidationError" : false,
                      "id" : "pbContainer",
                      "rows" : [
                        [
                          {
                            "type" : "component",
                            "dimension" : {
                              "md" : 12,
                              "sm" : 12,
                              "xs" : 12,
                              "lg" : 12
                            },
                            "propertyValues" : {
                              "allowHtml" : {
                                "type" : "constant",
                                "value" : true
                              },
                              "labelHidden" : {
                                "type" : "constant",
                                "value" : false
                              },
                              "hidden" : {
                                "type" : "expression",
                                "value" : "!evento.nombre"
                              },
                              "cssClasses" : {
                                "type" : "constant",
                                "value" : ""
                              },
                              "label" : {
                                "type" : "interpolation",
                                "value" : "Nombre"
                              },
                              "text" : {
                                "type" : "interpolation",
                                "value" : "{{evento.nombre}}"
                              },
                              "alignment" : {
                                "type" : "constant",
                                "value" : "left"
                              },
                              "dimension" : {
                                "type" : "constant",
                                "value" : 12
                              },
                              "labelPosition" : {
                                "type" : "constant",
                                "value" : "top"
                              },
                              "labelWidth" : {
                                "type" : "constant",
                                "value" : 12
                              },
                              "allowHTML" : {
                                "type" : "constant",
                                "value" : true
                              }
                            },
                            "reference" : "b30f559a-7d3a-4f76-ae57-4c204b089461",
                            "hasValidationError" : false,
                            "id" : "pbText",
                            "description" : ""
                          }
                        ],
                        [
                          {
                            "type" : "component",
                            "dimension" : {
                              "md" : 12,
                              "sm" : 12,
                              "xs" : 12,
                              "lg" : 12
                            },
                            "propertyValues" : {
                              "allowHtml" : {
                                "type" : "constant",
                                "value" : true
                              },
                              "labelHidden" : {
                                "type" : "constant",
                                "value" : false
                              },
                              "hidden" : {
                                "type" : "expression",
                                "value" : "!evento.descripcion"
                              },
                              "cssClasses" : {
                                "type" : "constant",
                                "value" : ""
                              },
                              "label" : {
                                "type" : "interpolation",
                                "value" : "Descripción"
                              },
                              "text" : {
                                "type" : "interpolation",
                                "value" : "{{evento.descripcion}}"
                              },
                              "alignment" : {
                                "type" : "constant",
                                "value" : "left"
                              },
                              "dimension" : {
                                "type" : "constant",
                                "value" : 12
                              },
                              "labelPosition" : {
                                "type" : "constant",
                                "value" : "top"
                              },
                              "labelWidth" : {
                                "type" : "constant",
                                "value" : 12
                              },
                              "allowHTML" : {
                                "type" : "constant",
                                "value" : true
                              }
                            },
                            "reference" : "41ff2e97-3ded-4d89-9a51-51fc03d5f437",
                            "hasValidationError" : false,
                            "id" : "pbText",
                            "description" : ""
                          }
                        ]
                      ]
                    },
                    {
                      "type" : "container",
                      "dimension" : {
                        "xs" : 6,
                        "sm" : 6,
                        "md" : 6,
                        "lg" : 6
                      },
                      "propertyValues" : {
                        "cssClasses" : {
                          "type" : "constant",
                          "value" : ""
                        },
                        "hidden" : {
                          "type" : "constant",
                          "value" : false
                        },
                        "repeatedCollection" : {
                          "type" : "variable",
                          "value" : ""
                        }
                      },
                      "reference" : "4faf2f65-f7ac-40fc-84ae-7114f58dec49",
                      "hasValidationError" : false,
                      "id" : "pbContainer",
                      "rows" : [
                        [
                          {
                            "type" : "component",
                            "dimension" : {
                              "xs" : 12,
                              "sm" : 12,
                              "md" : 12,
                              "lg" : 12
                            },
                            "propertyValues" : {
                              "cssClasses" : {
                                "type" : "constant",
                                "value" : ""
                              },
                              "hidden" : {
                                "type" : "constant",
                                "value" : false
                              },
                              "labelHidden" : {
                                "type" : "constant",
                                "value" : true
                              },
                              "label" : {
                                "type" : "interpolation",
                                "value" : "Default label"
                              },
                              "labelPosition" : {
                                "type" : "constant",
                                "value" : "top"
                              },
                              "labelWidth" : {
                                "type" : "constant",
                                "value" : 4
                              },
                              "allowHTML" : {
                                "type" : "constant",
                                "value" : true
                              },
                              "text" : {
                                "type" : "interpolation",
                                "value" : "<b>Imagen</b>"
                              },
                              "alignment" : {
                                "type" : "constant",
                                "value" : "center"
                              }
                            },
                            "reference" : "f9e9155f-b1c4-4ef1-a9ac-ea7ca64d7bc3",
                            "hasValidationError" : false,
                            "id" : "pbText"
                          }
                        ],
                        [
                          {
                            "type" : "component",
                            "dimension" : {
                              "xs" : 12,
                              "sm" : 12,
                              "md" : 12,
                              "lg" : 12
                            },
                            "propertyValues" : {
                              "cssClasses" : {
                                "type" : "constant",
                                "value" : ""
                              },
                              "hidden" : {
                                "type" : "constant",
                                "value" : false
                              },
                              "type" : {
                                "type" : "constant",
                                "value" : "Process document"
                              },
                              "url" : {
                                "type" : "constant",
                                "value" : ""
                              },
                              "document" : {
                                "type" : "variable",
                                "value" : "context.imagenEvento_ref"
                              },
                              "showPreview" : {
                                "type" : "constant",
                                "value" : true
                              }
                            },
                            "reference" : "b3e25e27-01df-4fc4-8766-dfef54054956",
                            "hasValidationError" : false,
                            "id" : "pbFileViewer"
                          }
                        ],
                        [
                          {
                            "type" : "component",
                            "dimension" : {
                              "xs" : 12,
                              "sm" : 12,
                              "md" : 12,
                              "lg" : 12
                            },
                            "propertyValues" : {
                              "cssClasses" : {
                                "type" : "constant",
                                "value" : ""
                              },
                              "hidden" : {
                                "type" : "constant",
                                "value" : false
                              },
                              "labelHidden" : {
                                "type" : "constant",
                                "value" : true
                              },
                              "label" : {
                                "type" : "interpolation",
                                "value" : "Default label"
                              },
                              "labelPosition" : {
                                "type" : "constant",
                                "value" : "top"
                              },
                              "labelWidth" : {
                                "type" : "constant",
                                "value" : 4
                              },
                              "allowHTML" : {
                                "type" : "constant",
                                "value" : true
                              },
                              "text" : {
                                "type" : "interpolation",
                                "value" : "Por favor tener en cuenta que la imagen del anuncio debe basarse en las imágenes institucionales que propone \"Imagen institucional\" {{evento.imagen}}"
                              },
                              "alignment" : {
                                "type" : "constant",
                                "value" : "left"
                              }
                            },
                            "reference" : "30fd1c94-d131-421b-b22a-563f7b8834e5",
                            "hasValidationError" : false,
                            "id" : "pbText"
                          }
                        ]
                      ]
                    }
                  ],
                  [
                    {
                      "type" : "container",
                      "dimension" : {
                        "xs" : 6,
                        "sm" : 6,
                        "md" : 6,
                        "lg" : 6
                      },
                      "propertyValues" : {
                        "cssClasses" : {
                          "type" : "constant",
                          "value" : ""
                        },
                        "hidden" : {
                          "type" : "constant",
                          "value" : false
                        },
                        "repeatedCollection" : {
                          "type" : "variable",
                          "value" : ""
                        }
                      },
                      "reference" : "b653db57-a5b1-448e-a5f6-c3d9b53924f2",
                      "hasValidationError" : false,
                      "id" : "pbContainer",
                      "rows" : [
                        [
                          {
                            "type" : "component",
                            "dimension" : {
                              "md" : 12,
                              "sm" : 12,
                              "xs" : 12,
                              "lg" : 12
                            },
                            "propertyValues" : {
                              "hidden" : {
                                "type" : "constant",
                                "value" : false
                              },
                              "level" : {
                                "type" : "constant",
                                "value" : "Level 5"
                              },
                              "cssClasses" : {
                                "type" : "constant",
                                "value" : ""
                              },
                              "text" : {
                                "type" : "interpolation",
                                "value" : "<b>Organizador/es<b>"
                              },
                              "alignment" : {
                                "type" : "constant",
                                "value" : "center"
                              },
                              "dimension" : {
                                "type" : "constant",
                                "value" : 12
                              }
                            },
                            "reference" : "dfcae8d2-361a-42c8-9664-68f07c0fb753",
                            "hasValidationError" : false,
                            "id" : "pbTitle",
                            "description" : ""
                          }
                        ],
                        [
                          {
                            "type" : "container",
                            "dimension" : {
                              "md" : 12,
                              "sm" : 12,
                              "xs" : 12,
                              "lg" : 12
                            },
                            "propertyValues" : {
                              "repeatedCollection" : {
                                "type" : "variable",
                                "value" : "evento.organizadores"
                              },
                              "hidden" : {
                                "type" : "constant",
                                "value" : false
                              },
                              "cssClasses" : {
                                "type" : "constant",
                                "value" : ""
                              },
                              "dimension" : {
                                "type" : "constant",
                                "value" : 12
                              }
                            },
                            "reference" : "a78ce4ad-ce36-4564-9e57-e15579800d4b",
                            "hasValidationError" : false,
                            "id" : "pbContainer",
                            "rows" : [
                              [
                                {
                                  "type" : "component",
                                  "dimension" : {
                                    "md" : 12,
                                    "sm" : 12,
                                    "xs" : 12,
                                    "lg" : 12
                                  },
                                  "propertyValues" : {
                                    "allowHtml" : {
                                      "type" : "constant",
                                      "value" : true
                                    },
                                    "labelHidden" : {
                                      "type" : "constant",
                                      "value" : true
                                    },
                                    "hidden" : {
                                      "type" : "expression",
                                      "value" : "!evento.organizadores"
                                    },
                                    "cssClasses" : {
                                      "type" : "constant",
                                      "value" : ""
                                    },
                                    "label" : {
                                      "type" : "interpolation",
                                      "value" : "Organizadores"
                                    },
                                    "text" : {
                                      "type" : "interpolation",
                                      "value" : "{{$item}}"
                                    },
                                    "alignment" : {
                                      "type" : "constant",
                                      "value" : "left"
                                    },
                                    "dimension" : {
                                      "type" : "constant",
                                      "value" : 12
                                    },
                                    "labelPosition" : {
                                      "type" : "constant",
                                      "value" : "top"
                                    },
                                    "labelWidth" : {
                                      "type" : "constant",
                                      "value" : 4
                                    },
                                    "allowHTML" : {
                                      "type" : "constant",
                                      "value" : true
                                    }
                                  },
                                  "reference" : "b5fa616c-4bcc-475d-b420-7a5190bb68ac",
                                  "hasValidationError" : false,
                                  "id" : "pbText",
                                  "description" : ""
                                }
                              ]
                            ]
                          }
                        ]
                      ]
                    },
                    {
                      "type" : "container",
                      "dimension" : {
                        "xs" : 6,
                        "sm" : 6,
                        "md" : 6,
                        "lg" : 6
                      },
                      "propertyValues" : {
                        "cssClasses" : {
                          "type" : "constant",
                          "value" : ""
                        },
                        "hidden" : {
                          "type" : "constant",
                          "value" : false
                        },
                        "repeatedCollection" : {
                          "type" : "variable",
                          "value" : ""
                        }
                      },
                      "reference" : "2f6e248d-fe00-4fe6-85bd-effe0480eaf2",
                      "hasValidationError" : false,
                      "id" : "pbContainer",
                      "rows" : [
                        [
                          {
                            "type" : "component",
                            "dimension" : {
                              "md" : 12,
                              "sm" : 12,
                              "xs" : 12,
                              "lg" : 12
                            },
                            "propertyValues" : {
                              "hidden" : {
                                "type" : "constant",
                                "value" : false
                              },
                              "level" : {
                                "type" : "constant",
                                "value" : "Level 5"
                              },
                              "cssClasses" : {
                                "type" : "constant",
                                "value" : ""
                              },
                              "text" : {
                                "type" : "interpolation",
                                "value" : "<b>Lugar/es<b>"
                              },
                              "alignment" : {
                                "type" : "constant",
                                "value" : "center"
                              },
                              "dimension" : {
                                "type" : "constant",
                                "value" : 12
                              }
                            },
                            "reference" : "e8bc43ac-e3de-47f7-8705-287510d126b8",
                            "hasValidationError" : false,
                            "id" : "pbTitle",
                            "description" : ""
                          }
                        ],
                        [
                          {
                            "type" : "container",
                            "dimension" : {
                              "md" : 12,
                              "sm" : 12,
                              "xs" : 12,
                              "lg" : 12
                            },
                            "propertyValues" : {
                              "repeatedCollection" : {
                                "type" : "variable",
                                "value" : "evento.lugares"
                              },
                              "hidden" : {
                                "type" : "constant",
                                "value" : false
                              },
                              "cssClasses" : {
                                "type" : "constant",
                                "value" : ""
                              },
                              "dimension" : {
                                "type" : "constant",
                                "value" : 12
                              }
                            },
                            "reference" : "9ea7b62a-a9b7-42fd-bb93-da52e85202bf",
                            "hasValidationError" : false,
                            "id" : "pbContainer",
                            "rows" : [
                              [
                                {
                                  "type" : "component",
                                  "dimension" : {
                                    "md" : 12,
                                    "sm" : 12,
                                    "xs" : 12,
                                    "lg" : 12
                                  },
                                  "propertyValues" : {
                                    "allowHtml" : {
                                      "type" : "constant",
                                      "value" : true
                                    },
                                    "labelHidden" : {
                                      "type" : "constant",
                                      "value" : true
                                    },
                                    "hidden" : {
                                      "type" : "expression",
                                      "value" : "!evento.lugares"
                                    },
                                    "cssClasses" : {
                                      "type" : "constant",
                                      "value" : ""
                                    },
                                    "label" : {
                                      "type" : "interpolation",
                                      "value" : "Lugares"
                                    },
                                    "text" : {
                                      "type" : "interpolation",
                                      "value" : "{{$item}}"
                                    },
                                    "alignment" : {
                                      "type" : "constant",
                                      "value" : "left"
                                    },
                                    "dimension" : {
                                      "type" : "constant",
                                      "value" : 12
                                    },
                                    "labelPosition" : {
                                      "type" : "constant",
                                      "value" : "top"
                                    },
                                    "labelWidth" : {
                                      "type" : "constant",
                                      "value" : 4
                                    },
                                    "allowHTML" : {
                                      "type" : "constant",
                                      "value" : true
                                    }
                                  },
                                  "reference" : "017bdaaf-d3d3-421d-bffa-9aca561a640a",
                                  "hasValidationError" : false,
                                  "id" : "pbText",
                                  "description" : ""
                                }
                              ]
                            ]
                          }
                        ]
                      ]
                    }
                  ],
                  [
                    {
                      "type" : "component",
                      "dimension" : {
                        "md" : 4,
                        "sm" : 4,
                        "xs" : 4,
                        "lg" : 4
                      },
                      "propertyValues" : {
                        "allowHtml" : {
                          "type" : "constant",
                          "value" : true
                        },
                        "labelHidden" : {
                          "type" : "constant",
                          "value" : false
                        },
                        "hidden" : {
                          "type" : "expression",
                          "value" : "!evento.tipoEvento"
                        },
                        "cssClasses" : {
                          "type" : "constant",
                          "value" : ""
                        },
                        "label" : {
                          "type" : "interpolation",
                          "value" : "Tipo de Evento"
                        },
                        "text" : {
                          "type" : "interpolation",
                          "value" : "{{evento.tipoEvento}}"
                        },
                        "alignment" : {
                          "type" : "constant",
                          "value" : "left"
                        },
                        "dimension" : {
                          "type" : "constant",
                          "value" : 12
                        },
                        "labelPosition" : {
                          "type" : "constant",
                          "value" : "top"
                        },
                        "labelWidth" : {
                          "type" : "constant",
                          "value" : 12
                        },
                        "allowHTML" : {
                          "type" : "constant",
                          "value" : true
                        }
                      },
                      "reference" : "7b793b86-03bd-4130-9086-cce6afdaf244",
                      "hasValidationError" : false,
                      "id" : "pbText",
                      "description" : ""
                    },
                    {
                      "type" : "component",
                      "dimension" : {
                        "md" : 4,
                        "sm" : 4,
                        "xs" : 4,
                        "lg" : 4
                      },
                      "propertyValues" : {
                        "allowHtml" : {
                          "type" : "constant",
                          "value" : true
                        },
                        "labelHidden" : {
                          "type" : "constant",
                          "value" : false
                        },
                        "hidden" : {
                          "type" : "expression",
                          "value" : "!evento.categoriaEvento"
                        },
                        "cssClasses" : {
                          "type" : "constant",
                          "value" : ""
                        },
                        "label" : {
                          "type" : "interpolation",
                          "value" : "Categoría de Evento"
                        },
                        "text" : {
                          "type" : "interpolation",
                          "value" : "{{evento.categoriaEvento}}"
                        },
                        "alignment" : {
                          "type" : "constant",
                          "value" : "left"
                        },
                        "dimension" : {
                          "type" : "constant",
                          "value" : 12
                        },
                        "labelPosition" : {
                          "type" : "constant",
                          "value" : "top"
                        },
                        "labelWidth" : {
                          "type" : "constant",
                          "value" : 12
                        },
                        "allowHTML" : {
                          "type" : "constant",
                          "value" : true
                        }
                      },
                      "reference" : "16c0d034-2cf1-40c1-a1aa-e0368b8063a7",
                      "hasValidationError" : false,
                      "id" : "pbText",
                      "description" : ""
                    },
                    {
                      "type" : "component",
                      "dimension" : {
                        "md" : 4,
                        "sm" : 4,
                        "xs" : 4,
                        "lg" : 4
                      },
                      "propertyValues" : {
                        "allowHtml" : {
                          "type" : "constant",
                          "value" : true
                        },
                        "labelHidden" : {
                          "type" : "constant",
                          "value" : false
                        },
                        "hidden" : {
                          "type" : "expression",
                          "value" : "!evento.cupo"
                        },
                        "cssClasses" : {
                          "type" : "constant",
                          "value" : ""
                        },
                        "label" : {
                          "type" : "interpolation",
                          "value" : "Cupo"
                        },
                        "text" : {
                          "type" : "interpolation",
                          "value" : "{{evento.cupo}}"
                        },
                        "alignment" : {
                          "type" : "constant",
                          "value" : "left"
                        },
                        "dimension" : {
                          "type" : "constant",
                          "value" : 12
                        },
                        "labelPosition" : {
                          "type" : "constant",
                          "value" : "top"
                        },
                        "labelWidth" : {
                          "type" : "constant",
                          "value" : 12
                        },
                        "allowHTML" : {
                          "type" : "constant",
                          "value" : true
                        }
                      },
                      "reference" : "a61855c6-536c-4680-ac11-b7251bca68b0",
                      "hasValidationError" : false,
                      "id" : "pbText",
                      "description" : ""
                    }
                  ],
                  [
                    {
                      "type" : "container",
                      "dimension" : {
                        "xs" : 12,
                        "sm" : 12,
                        "md" : 12,
                        "lg" : 12
                      },
                      "propertyValues" : {
                        "cssClasses" : {
                          "type" : "constant",
                          "value" : ""
                        },
                        "hidden" : {
                          "type" : "constant",
                          "value" : false
                        },
                        "repeatedCollection" : {
                          "type" : "variable",
                          "value" : ""
                        }
                      },
                      "reference" : "d96ad7d6-a4d3-4848-9bde-a88c21f1abaf",
                      "hasValidationError" : false,
                      "id" : "pbContainer",
                      "rows" : [
                        [
                          {
                            "type" : "component",
                            "dimension" : {
                              "md" : 12,
                              "sm" : 12,
                              "xs" : 12,
                              "lg" : 12
                            },
                            "propertyValues" : {
                              "hidden" : {
                                "type" : "constant",
                                "value" : false
                              },
                              "level" : {
                                "type" : "constant",
                                "value" : "Level 5"
                              },
                              "cssClasses" : {
                                "type" : "constant",
                                "value" : ""
                              },
                              "text" : {
                                "type" : "interpolation",
                                "value" : "<b>Valor/es<b>"
                              },
                              "alignment" : {
                                "type" : "constant",
                                "value" : "center"
                              },
                              "dimension" : {
                                "type" : "constant",
                                "value" : 12
                              }
                            },
                            "reference" : "97638777-7475-40a5-99d2-ed2965f0308c",
                            "hasValidationError" : false,
                            "id" : "pbTitle",
                            "description" : ""
                          }
                        ],
                        [
                          {
                            "type" : "container",
                            "dimension" : {
                              "md" : 12,
                              "sm" : 12,
                              "xs" : 12,
                              "lg" : 12
                            },
                            "propertyValues" : {
                              "repeatedCollection" : {
                                "type" : "variable",
                                "value" : "evento_valor"
                              },
                              "hidden" : {
                                "type" : "constant",
                                "value" : false
                              },
                              "cssClasses" : {
                                "type" : "constant",
                                "value" : ""
                              },
                              "dimension" : {
                                "type" : "constant",
                                "value" : 12
                              }
                            },
                            "reference" : "b466a644-568b-4afa-8609-352eb6992ead",
                            "hasValidationError" : false,
                            "id" : "pbContainer",
                            "rows" : [
                              [
                                {
                                  "type" : "component",
                                  "dimension" : {
                                    "md" : 6,
                                    "sm" : 6,
                                    "xs" : 6,
                                    "lg" : 6
                                  },
                                  "propertyValues" : {
                                    "allowHtml" : {
                                      "type" : "constant",
                                      "value" : true
                                    },
                                    "labelHidden" : {
                                      "type" : "constant",
                                      "value" : false
                                    },
                                    "hidden" : {
                                      "type" : "expression",
                                      "value" : "!$item.rol"
                                    },
                                    "cssClasses" : {
                                      "type" : "constant",
                                      "value" : ""
                                    },
                                    "label" : {
                                      "type" : "interpolation",
                                      "value" : "Rol"
                                    },
                                    "text" : {
                                      "type" : "interpolation",
                                      "value" : "{{$item.rol}}"
                                    },
                                    "alignment" : {
                                      "type" : "constant",
                                      "value" : "left"
                                    },
                                    "dimension" : {
                                      "type" : "constant",
                                      "value" : 12
                                    },
                                    "labelPosition" : {
                                      "type" : "constant",
                                      "value" : "top"
                                    },
                                    "labelWidth" : {
                                      "type" : "constant",
                                      "value" : 12
                                    },
                                    "allowHTML" : {
                                      "type" : "constant",
                                      "value" : true
                                    }
                                  },
                                  "reference" : "770dea40-2c45-41b2-8074-38354d01489f",
                                  "hasValidationError" : false,
                                  "id" : "pbText",
                                  "description" : ""
                                },
                                {
                                  "type" : "component",
                                  "dimension" : {
                                    "md" : 6,
                                    "sm" : 6,
                                    "xs" : 6,
                                    "lg" : 6
                                  },
                                  "propertyValues" : {
                                    "allowHtml" : {
                                      "type" : "constant",
                                      "value" : true
                                    },
                                    "labelHidden" : {
                                      "type" : "constant",
                                      "value" : false
                                    },
                                    "hidden" : {
                                      "type" : "constant",
                                      "value" : false
                                    },
                                    "cssClasses" : {
                                      "type" : "constant",
                                      "value" : ""
                                    },
                                    "label" : {
                                      "type" : "interpolation",
                                      "value" : "Valor"
                                    },
                                    "text" : {
                                      "type" : "interpolation",
                                      "value" : "{{$item.valor}}"
                                    },
                                    "alignment" : {
                                      "type" : "constant",
                                      "value" : "left"
                                    },
                                    "dimension" : {
                                      "type" : "constant",
                                      "value" : 12
                                    },
                                    "labelPosition" : {
                                      "type" : "constant",
                                      "value" : "top"
                                    },
                                    "labelWidth" : {
                                      "type" : "constant",
                                      "value" : 12
                                    },
                                    "allowHTML" : {
                                      "type" : "constant",
                                      "value" : true
                                    }
                                  },
                                  "reference" : "4d25f340-83ef-4493-9878-dbcd2fb4f542",
                                  "hasValidationError" : false,
                                  "id" : "pbText",
                                  "description" : ""
                                }
                              ]
                            ]
                          }
                        ]
                      ]
                    }
                  ],
                  [
                    {
                      "type" : "component",
                      "dimension" : {
                        "md" : 12,
                        "sm" : 12,
                        "xs" : 12,
                        "lg" : 12
                      },
                      "propertyValues" : {
                        "hidden" : {
                          "type" : "constant",
                          "value" : false
                        },
                        "level" : {
                          "type" : "constant",
                          "value" : "Level 5"
                        },
                        "cssClasses" : {
                          "type" : "constant",
                          "value" : ""
                        },
                        "text" : {
                          "type" : "interpolation",
                          "value" : "<b>Ponente/s<b>"
                        },
                        "alignment" : {
                          "type" : "constant",
                          "value" : "center"
                        },
                        "dimension" : {
                          "type" : "constant",
                          "value" : 12
                        }
                      },
                      "reference" : "5bc18eeb-ff45-4945-a841-55f1896cc9c7",
                      "hasValidationError" : false,
                      "id" : "pbTitle",
                      "description" : ""
                    }
                  ],
                  [
                    {
                      "type" : "container",
                      "dimension" : {
                        "md" : 12,
                        "sm" : 12,
                        "xs" : 12,
                        "lg" : 12
                      },
                      "propertyValues" : {
                        "repeatedCollection" : {
                          "type" : "variable",
                          "value" : "evento_ponentes"
                        },
                        "hidden" : {
                          "type" : "constant",
                          "value" : false
                        },
                        "cssClasses" : {
                          "type" : "constant",
                          "value" : ""
                        },
                        "dimension" : {
                          "type" : "constant",
                          "value" : 12
                        }
                      },
                      "reference" : "7ad4718d-11f4-473c-b8a4-bbbd4c6a7311",
                      "hasValidationError" : false,
                      "id" : "pbContainer",
                      "rows" : [
                        [
                          {
                            "type" : "component",
                            "dimension" : {
                              "md" : 4,
                              "sm" : 4,
                              "xs" : 4,
                              "lg" : 4
                            },
                            "propertyValues" : {
                              "allowHtml" : {
                                "type" : "constant",
                                "value" : true
                              },
                              "labelHidden" : {
                                "type" : "constant",
                                "value" : false
                              },
                              "hidden" : {
                                "type" : "expression",
                                "value" : "!$item.nombre"
                              },
                              "cssClasses" : {
                                "type" : "constant",
                                "value" : ""
                              },
                              "label" : {
                                "type" : "interpolation",
                                "value" : "Nombre"
                              },
                              "text" : {
                                "type" : "interpolation",
                                "value" : "{{$item.nombre}}"
                              },
                              "alignment" : {
                                "type" : "constant",
                                "value" : "left"
                              },
                              "dimension" : {
                                "type" : "constant",
                                "value" : 12
                              },
                              "labelPosition" : {
                                "type" : "constant",
                                "value" : "top"
                              },
                              "labelWidth" : {
                                "type" : "constant",
                                "value" : 12
                              },
                              "allowHTML" : {
                                "type" : "constant",
                                "value" : true
                              }
                            },
                            "reference" : "73b82784-c9ee-4daf-9f65-a880a9eaae04",
                            "hasValidationError" : false,
                            "id" : "pbText",
                            "description" : ""
                          },
                          {
                            "type" : "component",
                            "dimension" : {
                              "md" : 4,
                              "sm" : 4,
                              "xs" : 4,
                              "lg" : 4
                            },
                            "propertyValues" : {
                              "allowHtml" : {
                                "type" : "constant",
                                "value" : true
                              },
                              "labelHidden" : {
                                "type" : "constant",
                                "value" : false
                              },
                              "hidden" : {
                                "type" : "expression",
                                "value" : "!$item.apellido"
                              },
                              "cssClasses" : {
                                "type" : "constant",
                                "value" : ""
                              },
                              "label" : {
                                "type" : "interpolation",
                                "value" : "Apellido"
                              },
                              "text" : {
                                "type" : "interpolation",
                                "value" : "{{$item.apellido}}"
                              },
                              "alignment" : {
                                "type" : "constant",
                                "value" : "left"
                              },
                              "dimension" : {
                                "type" : "constant",
                                "value" : 12
                              },
                              "labelPosition" : {
                                "type" : "constant",
                                "value" : "top"
                              },
                              "labelWidth" : {
                                "type" : "constant",
                                "value" : 12
                              },
                              "allowHTML" : {
                                "type" : "constant",
                                "value" : true
                              }
                            },
                            "reference" : "9e3f5576-0db3-4da0-a62e-661c2a82a350",
                            "hasValidationError" : false,
                            "id" : "pbText",
                            "description" : ""
                          },
                          {
                            "type" : "component",
                            "dimension" : {
                              "md" : 4,
                              "sm" : 4,
                              "xs" : 4,
                              "lg" : 4
                            },
                            "propertyValues" : {
                              "allowHtml" : {
                                "type" : "constant",
                                "value" : true
                              },
                              "labelHidden" : {
                                "type" : "constant",
                                "value" : false
                              },
                              "hidden" : {
                                "type" : "expression",
                                "value" : "!$item.correo"
                              },
                              "cssClasses" : {
                                "type" : "constant",
                                "value" : ""
                              },
                              "label" : {
                                "type" : "interpolation",
                                "value" : "Correo"
                              },
                              "text" : {
                                "type" : "interpolation",
                                "value" : "{{$item.correo}}"
                              },
                              "alignment" : {
                                "type" : "constant",
                                "value" : "left"
                              },
                              "dimension" : {
                                "type" : "constant",
                                "value" : 12
                              },
                              "labelPosition" : {
                                "type" : "constant",
                                "value" : "top"
                              },
                              "labelWidth" : {
                                "type" : "constant",
                                "value" : 12
                              },
                              "allowHTML" : {
                                "type" : "constant",
                                "value" : true
                              }
                            },
                            "reference" : "a3a06e2f-a828-46ee-bb97-cd3fcf39bc17",
                            "hasValidationError" : false,
                            "id" : "pbText",
                            "description" : ""
                          }
                        ],
                        [
                          {
                            "type" : "component",
                            "dimension" : {
                              "md" : 12,
                              "sm" : 12,
                              "xs" : 12,
                              "lg" : 12
                            },
                            "propertyValues" : {
                              "allowHtml" : {
                                "type" : "constant",
                                "value" : true
                              },
                              "labelHidden" : {
                                "type" : "constant",
                                "value" : false
                              },
                              "hidden" : {
                                "type" : "expression",
                                "value" : "!$item.resumen"
                              },
                              "cssClasses" : {
                                "type" : "constant",
                                "value" : ""
                              },
                              "label" : {
                                "type" : "interpolation",
                                "value" : "Resumen"
                              },
                              "text" : {
                                "type" : "interpolation",
                                "value" : "{{$item.resumen}}"
                              },
                              "alignment" : {
                                "type" : "constant",
                                "value" : "left"
                              },
                              "dimension" : {
                                "type" : "constant",
                                "value" : 12
                              },
                              "labelPosition" : {
                                "type" : "constant",
                                "value" : "top"
                              },
                              "labelWidth" : {
                                "type" : "constant",
                                "value" : 12
                              },
                              "allowHTML" : {
                                "type" : "constant",
                                "value" : true
                              }
                            },
                            "reference" : "5e18a13f-0ec6-4be2-bb2c-9b6146c3bd58",
                            "hasValidationError" : false,
                            "id" : "pbText",
                            "description" : ""
                          }
                        ]
                      ]
                    }
                  ],
                  [
                    {
                      "type" : "component",
                      "dimension" : {
                        "md" : 6,
                        "sm" : 6,
                        "xs" : 6,
                        "lg" : 6
                      },
                      "propertyValues" : {
                        "allowHtml" : {
                          "type" : "constant",
                          "value" : true
                        },
                        "labelHidden" : {
                          "type" : "constant",
                          "value" : false
                        },
                        "hidden" : {
                          "type" : "expression",
                          "value" : "!evento.fechaInscripcionInicio"
                        },
                        "cssClasses" : {
                          "type" : "constant",
                          "value" : ""
                        },
                        "label" : {
                          "type" : "interpolation",
                          "value" : "Fecha de Inicio de Inscripciones"
                        },
                        "text" : {
                          "type" : "interpolation",
                          "value" : "{{evento.fechaInscripcionInicio|uiDate}}"
                        },
                        "alignment" : {
                          "type" : "constant",
                          "value" : "left"
                        },
                        "dimension" : {
                          "type" : "constant",
                          "value" : 12
                        },
                        "labelPosition" : {
                          "type" : "constant",
                          "value" : "top"
                        },
                        "labelWidth" : {
                          "type" : "constant",
                          "value" : 12
                        },
                        "allowHTML" : {
                          "type" : "constant",
                          "value" : true
                        }
                      },
                      "reference" : "bdeb6ff6-5958-4088-a50c-af4d0cc5939b",
                      "hasValidationError" : false,
                      "id" : "pbText",
                      "description" : ""
                    },
                    {
                      "type" : "component",
                      "dimension" : {
                        "md" : 6,
                        "sm" : 6,
                        "xs" : 6,
                        "lg" : 6
                      },
                      "propertyValues" : {
                        "allowHtml" : {
                          "type" : "constant",
                          "value" : true
                        },
                        "labelHidden" : {
                          "type" : "constant",
                          "value" : false
                        },
                        "hidden" : {
                          "type" : "expression",
                          "value" : "!evento.fechaInscripcionFin"
                        },
                        "cssClasses" : {
                          "type" : "constant",
                          "value" : ""
                        },
                        "label" : {
                          "type" : "interpolation",
                          "value" : "Fecha de Finalización de Inscripciones"
                        },
                        "text" : {
                          "type" : "interpolation",
                          "value" : "{{evento.fechaInscripcionFin|uiDate}}"
                        },
                        "alignment" : {
                          "type" : "constant",
                          "value" : "left"
                        },
                        "dimension" : {
                          "type" : "constant",
                          "value" : 12
                        },
                        "labelPosition" : {
                          "type" : "constant",
                          "value" : "top"
                        },
                        "labelWidth" : {
                          "type" : "constant",
                          "value" : 12
                        },
                        "allowHTML" : {
                          "type" : "constant",
                          "value" : true
                        }
                      },
                      "reference" : "514ae912-b51e-42f0-8c22-1aee8ed3f2b3",
                      "hasValidationError" : false,
                      "id" : "pbText",
                      "description" : ""
                    }
                  ],
                  [
                    {
                      "type" : "component",
                      "dimension" : {
                        "md" : 6,
                        "sm" : 6,
                        "xs" : 6,
                        "lg" : 6
                      },
                      "propertyValues" : {
                        "allowHtml" : {
                          "type" : "constant",
                          "value" : true
                        },
                        "labelHidden" : {
                          "type" : "constant",
                          "value" : false
                        },
                        "hidden" : {
                          "type" : "expression",
                          "value" : "!evento.fechaEventoInicio"
                        },
                        "cssClasses" : {
                          "type" : "constant",
                          "value" : ""
                        },
                        "label" : {
                          "type" : "interpolation",
                          "value" : "Fecha de Inicio de Evento"
                        },
                        "text" : {
                          "type" : "interpolation",
                          "value" : "{{evento.fechaEventoInicio|uiDate}}"
                        },
                        "alignment" : {
                          "type" : "constant",
                          "value" : "left"
                        },
                        "dimension" : {
                          "type" : "constant",
                          "value" : 12
                        },
                        "labelPosition" : {
                          "type" : "constant",
                          "value" : "top"
                        },
                        "labelWidth" : {
                          "type" : "constant",
                          "value" : 12
                        },
                        "allowHTML" : {
                          "type" : "constant",
                          "value" : true
                        }
                      },
                      "reference" : "d1db8831-73c6-420f-9d41-2afdf5ff5775",
                      "hasValidationError" : false,
                      "id" : "pbText",
                      "description" : ""
                    },
                    {
                      "type" : "component",
                      "dimension" : {
                        "md" : 6,
                        "sm" : 6,
                        "xs" : 6,
                        "lg" : 6
                      },
                      "propertyValues" : {
                        "allowHtml" : {
                          "type" : "constant",
                          "value" : true
                        },
                        "labelHidden" : {
                          "type" : "constant",
                          "value" : false
                        },
                        "hidden" : {
                          "type" : "expression",
                          "value" : "!evento.fechaEventoFin"
                        },
                        "cssClasses" : {
                          "type" : "constant",
                          "value" : ""
                        },
                        "label" : {
                          "type" : "interpolation",
                          "value" : "Fecha de Finalización de Evento"
                        },
                        "text" : {
                          "type" : "interpolation",
                          "value" : "{{evento.fechaEventoFin|uiDate}}"
                        },
                        "alignment" : {
                          "type" : "constant",
                          "value" : "left"
                        },
                        "dimension" : {
                          "type" : "constant",
                          "value" : 12
                        },
                        "labelPosition" : {
                          "type" : "constant",
                          "value" : "top"
                        },
                        "labelWidth" : {
                          "type" : "constant",
                          "value" : 12
                        },
                        "allowHTML" : {
                          "type" : "constant",
                          "value" : true
                        }
                      },
                      "reference" : "c9dec1aa-e8ce-469b-90ad-9157e669dcab",
                      "hasValidationError" : false,
                      "id" : "pbText",
                      "description" : ""
                    }
                  ],
                  [
                    {
                      "type" : "component",
                      "dimension" : {
                        "md" : 12,
                        "sm" : 12,
                        "xs" : 12,
                        "lg" : 12
                      },
                      "propertyValues" : {
                        "allowHtml" : {
                          "type" : "constant",
                          "value" : true
                        },
                        "labelHidden" : {
                          "type" : "constant",
                          "value" : false
                        },
                        "hidden" : {
                          "type" : "expression",
                          "value" : "!evento.fechaSolicitud"
                        },
                        "cssClasses" : {
                          "type" : "constant",
                          "value" : ""
                        },
                        "label" : {
                          "type" : "interpolation",
                          "value" : "Fecha de Solicitud"
                        },
                        "text" : {
                          "type" : "interpolation",
                          "value" : "{{evento.fechaSolicitud|uiDate}}"
                        },
                        "alignment" : {
                          "type" : "constant",
                          "value" : "left"
                        },
                        "dimension" : {
                          "type" : "constant",
                          "value" : 12
                        },
                        "labelPosition" : {
                          "type" : "constant",
                          "value" : "top"
                        },
                        "labelWidth" : {
                          "type" : "constant",
                          "value" : 12
                        },
                        "allowHTML" : {
                          "type" : "constant",
                          "value" : true
                        }
                      },
                      "reference" : "c34c4ddf-ddf0-4e9e-b5d6-f39de09f1620",
                      "hasValidationError" : false,
                      "id" : "pbText",
                      "description" : ""
                    }
                  ],
                  [
                    {
                      "type" : "component",
                      "dimension" : {
                        "xs" : 12,
                        "sm" : 12,
                        "md" : 12,
                        "lg" : 12
                      },
                      "propertyValues" : {
                        "cssClasses" : {
                          "type" : "constant",
                          "value" : ""
                        },
                        "hidden" : {
                          "type" : "constant",
                          "value" : false
                        },
                        "labelHidden" : {
                          "type" : "constant",
                          "value" : true
                        },
                        "label" : {
                          "type" : "interpolation",
                          "value" : "Default label"
                        },
                        "labelPosition" : {
                          "type" : "constant",
                          "value" : "top"
                        },
                        "labelWidth" : {
                          "type" : "constant",
                          "value" : 4
                        },
                        "allowHTML" : {
                          "type" : "constant",
                          "value" : true
                        },
                        "text" : {
                          "type" : "interpolation",
                          "value" : "<b>Cronograma</b>"
                        },
                        "alignment" : {
                          "type" : "constant",
                          "value" : "center"
                        }
                      },
                      "reference" : "c556e744-1747-414a-b15b-02187378f19a",
                      "hasValidationError" : false,
                      "id" : "pbText"
                    }
                  ],
                  [
                    {
                      "type" : "component",
                      "dimension" : {
                        "xs" : 12,
                        "sm" : 12,
                        "md" : 12,
                        "lg" : 12
                      },
                      "propertyValues" : {
                        "cssClasses" : {
                          "type" : "constant",
                          "value" : ""
                        },
                        "hidden" : {
                          "type" : "constant",
                          "value" : false
                        },
                        "type" : {
                          "type" : "constant",
                          "value" : "Process document"
                        },
                        "url" : {
                          "type" : "constant",
                          "value" : ""
                        },
                        "document" : {
                          "type" : "variable",
                          "value" : "context.cronogramaEvento_ref"
                        },
                        "showPreview" : {
                          "type" : "constant",
                          "value" : true
                        }
                      },
                      "reference" : "ac3fff26-6f9c-4fd0-9474-3847d9b73868",
                      "hasValidationError" : false,
                      "id" : "pbFileViewer"
                    }
                  ]
                ]
              }
            ],
            [
              {
                "type" : "component",
                "dimension" : {
                  "md" : 12,
                  "sm" : 12,
                  "xs" : 12,
                  "lg" : 12
                },
                "propertyValues" : {
                  "cssClasses" : {
                    "type" : "constant",
                    "value" : ""
                  },
                  "hidden" : {
                    "type" : "constant",
                    "value" : false
                  },
                  "readOnly" : {
                    "type" : "constant",
                    "value" : false
                  },
                  "required" : {
                    "type" : "constant",
                    "value" : true
                  },
                  "minLength" : {
                    "type" : "constant",
                    "value" : ""
                  },
                  "maxLength" : {
                    "type" : "constant",
                    "value" : ""
                  },
                  "labelHidden" : {
                    "type" : "constant",
                    "value" : false
                  },
                  "label" : {
                    "type" : "interpolation",
                    "value" : "Comentario"
                  },
                  "labelPosition" : {
                    "type" : "constant",
                    "value" : "top"
                  },
                  "labelWidth" : {
                    "type" : "constant",
                    "value" : 12
                  },
                  "value" : {
                    "type" : "variable",
                    "value" : "formInput.comentarioInput"
                  }
                },
                "reference" : "832cb021-7866-42f0-8f2d-f88ddf1f12f8",
                "hasValidationError" : false,
                "id" : "pbTextarea"
              }
            ],
            [
              {
                "type" : "component",
                "dimension" : {
                  "md" : 12,
                  "sm" : 12,
                  "xs" : 12,
                  "lg" : 12
                },
                "propertyValues" : {
                  "labelHidden" : {
                    "type" : "constant",
                    "value" : false
                  },
                  "hidden" : {
                    "type" : "constant",
                    "value" : false
                  },
                  "cssClasses" : {
                    "type" : "constant",
                    "value" : ""
                  },
                  "disabled" : {
                    "type" : "constant",
                    "value" : false
                  },
                  "label" : {
                    "type" : "interpolation",
                    "value" : "Validado"
                  },
                  "dimension" : {
                    "type" : "constant",
                    "value" : 12
                  },
                  "value" : {
                    "type" : "variable",
                    "value" : "evento.validado"
                  },
                  "required" : {
                    "type" : "constant",
                    "value" : false
                  }
                },
                "reference" : "aa280150-5ce2-4db3-8b5f-e9bf792ac04e",
                "hasValidationError" : false,
                "id" : "pbCheckbox",
                "description" : ""
              }
            ],
            [
              {
                "type" : "component",
                "dimension" : {
                  "md" : 12,
                  "sm" : 12,
                  "xs" : 12,
                  "lg" : 12
                },
                "propertyValues" : {
                  "removeItem" : {
                    "type" : "variable"
                  },
                  "hidden" : {
                    "type" : "constant",
                    "value" : false
                  },
                  "cssClasses" : {
                    "type" : "constant",
                    "value" : ""
                  },
                  "buttonStyle" : {
                    "type" : "constant",
                    "value" : "primary"
                  },
                  "label" : {
                    "type" : "interpolation",
                    "value" : "Aceptar"
                  },
                  "dataToSend" : {
                    "type" : "expression",
                    "value" : "formOutput"
                  },
                  "dataFromError" : {
                    "type" : "variable",
                    "value" : "formOutput._submitError"
                  },
                  "labelHidden" : {
                    "type" : "constant",
                    "value" : false
                  },
                  "collectionPosition" : {
                    "type" : "constant"
                  },
                  "targetUrlOnSuccess" : {
                    "type" : "interpolation",
                    "value" : "/bonita"
                  },
                  "action" : {
                    "type" : "constant",
                    "value" : "Submit task"
                  },
                  "collectionToModify" : {
                    "type" : "variable"
                  },
                  "valueToAdd" : {
                    "type" : "expression"
                  },
                  "disabled" : {
                    "type" : "expression",
                    "value" : "$form.$invalid"
                  },
                  "alignment" : {
                    "type" : "constant",
                    "value" : "center"
                  },
                  "dimension" : {
                    "type" : "constant",
                    "value" : 12
                  },
                  "assign" : {
                    "type" : "constant",
                    "value" : false
                  },
                  "url" : {
                    "type" : "interpolation"
                  },
                  "responseStatusCode" : {
                    "type" : "variable",
                    "value" : ""
                  },
                  "dataFromSuccess" : {
                    "type" : "variable",
                    "value" : ""
                  },
                  "closeOnSuccess" : {
                    "type" : "constant",
                    "value" : false
                  },
                  "modalId" : {
                    "type" : "constant",
                    "value" : ""
                  }
                },
                "reference" : "de8ab46b-11c4-46a8-9f0a-4f463d013806",
                "hasValidationError" : false,
                "id" : "pbButton",
                "description" : ""
              }
            ],
            [
              {
                "type" : "component",
                "dimension" : {
                  "md" : 12,
                  "sm" : 12,
                  "xs" : 12,
                  "lg" : 12
                },
                "propertyValues" : {
                  "allowHTML" : {
                    "type" : "constant",
                    "value" : true
                  },
                  "allowHtml" : {
                    "type" : "constant",
                    "value" : true
                  },
                  "labelHidden" : {
                    "type" : "constant",
                    "value" : true
                  },
                  "hidden" : {
                    "type" : "expression",
                    "value" : "!formOutput._submitError.message"
                  },
                  "cssClasses" : {
                    "type" : "constant",
                    "value" : "alert alert-danger col-lg-6 col-lg-offset-3"
                  },
                  "label" : {
                    "type" : "interpolation"
                  },
                  "text" : {
                    "type" : "interpolation",
                    "value" : "<strong>Debug message</strong>\n<br/>\n{{formOutput._submitError.message}}\n{{submit_errors_list}}"
                  },
                  "alignment" : {
                    "type" : "constant",
                    "value" : "center"
                  },
                  "dimension" : {
                    "type" : "constant",
                    "value" : 12
                  },
                  "labelPosition" : {
                    "type" : "constant",
                    "value" : "top"
                  },
                  "labelWidth" : {
                    "type" : "constant",
                    "value" : 4
                  }
                },
                "reference" : "76668c68-9b34-40a8-a346-70fe6f683cf7",
                "hasValidationError" : false,
                "id" : "pbText",
                "description" : ""
              }
            ]
          ]
        }
      }
    ],
    [
      {
        "type" : "component",
        "dimension" : {
          "xs" : 12,
          "sm" : 12,
          "md" : 12,
          "lg" : 12
        },
        "propertyValues" : {
          "cssClasses" : {
            "type" : "constant",
            "value" : ""
          },
          "hidden" : {
            "type" : "constant",
            "value" : false
          },
          "text" : {
            "type" : "constant",
            "value" : "Desarrollado completamente en BonitaSoft"
          }
        },
        "reference" : "d7f68e2c-7929-4408-a42c-f1e424f247b0",
        "hasValidationError" : false,
        "id" : "customFooter"
      }
    ]
  ],
  "assets" : [
    {
      "id" : "d7fc260e-ce34-4def-a18f-69b9df76ac50",
      "name" : "style.css",
      "type" : "css",
      "order" : 0,
      "external" : false
    },
    {
      "id" : "d4d4d2b8-71d5-4159-84b2-4d26f4cc25a7",
      "name" : "localization.json",
      "type" : "json",
      "order" : 0,
      "external" : false
    }
  ],
  "inactiveAssets" : [ ],
  "variables" : {
    "evento" : {
      "type" : "url",
      "value" : [
        "../{{context.evento_ref.link}}"
      ],
      "exposed" : false
    },
    "task" : {
      "type" : "url",
      "value" : [
        "../API/bpm/userTask/{{taskId}}"
      ],
      "exposed" : false
    },
    "formInput" : {
      "type" : "json",
      "value" : [
        "{",
        "  \"comentarioInput\" : \"\"",
        "}"
      ],
      "exposed" : false
    },
    "evento_ponentes" : {
      "type" : "url",
      "value" : [
        "{{evento|lazyRef:'ponentes'}}"
      ],
      "exposed" : false
    },
    "submit_errors_list" : {
      "type" : "expression",
      "value" : [
        "if($data.formOutput && $data.formOutput._submitError && $data.formOutput._submitError.explanations){",
        "\tconst liElements = $data.formOutput._submitError.explanations",
        "\t\t.filter(cause => cause !== null)",
        "\t\t.map(cause => \"<li>\" + cause + \"</li>\")",
        "\t\t.join('');",
        "\tif(liElements){",
        "\t\treturn \"<ul>\" + liElements + \"</ul>\";",
        "\t}",
        "}"
      ],
      "exposed" : false
    },
    "formOutput" : {
      "type" : "expression",
      "value" : [
        "if( $data.evento && $data.evento_valor && $data.evento_ponentes ){",
        "\t//attach lazy references variables to parent variables",
        "\t$data.evento.valor = $data.evento_valor;",
        "\t$data.evento.ponentes = $data.evento_ponentes;",
        "\treturn {",
        "\t\tcomentarioInput: $data.formInput.comentarioInput,",
        "\t\t//map evento variable to expected task contract input",
        "\t\teventoInput: {",
        "\t\t\tvalidado: $data.evento.validado !== undefined ? $data.evento.validado : null",
        "\t\t}",
        "\t}",
        "}"
      ],
      "exposed" : false
    },
    "context" : {
      "type" : "url",
      "value" : [
        "../API/bpm/userTask/{{taskId}}/context"
      ],
      "exposed" : false
    },
    "evento_valor" : {
      "type" : "url",
      "value" : [
        "{{evento|lazyRef:'valor'}}"
      ],
      "exposed" : false
    },
    "taskId" : {
      "type" : "urlparameter",
      "value" : [
        "id"
      ],
      "exposed" : false
    },
    "usuarioSolicitante" : {
      "type" : "url",
      "value" : [
        "../API/bpm/activityVariable/{{taskId}}/usuarioSolicitante"
      ],
      "exposed" : false
    }
  },
  "hasValidationError" : false,
  "uuid" : "d04c0340-68a8-4279-925c-c57c06005030",
  "type" : "form",
  "description" : "Page generated with Bonita UI designer"
}